odoo/addons/sale_commission_salesman/README.rst
odoo/addons/sale_commission_salesman/__init__.py
odoo/addons/sale_commission_salesman/__manifest__.py
odoo/addons/sale_commission_salesman/i18n/es.po
odoo/addons/sale_commission_salesman/i18n/pt.po
odoo/addons/sale_commission_salesman/i18n/pt_BR.po
odoo/addons/sale_commission_salesman/i18n/sale_commission_salesman.pot
odoo/addons/sale_commission_salesman/models/__init__.py
odoo/addons/sale_commission_salesman/models/account_invoice.py
odoo/addons/sale_commission_salesman/models/res_partner.py
odoo/addons/sale_commission_salesman/models/sale_order.py
odoo/addons/sale_commission_salesman/readme/CONFIGURE.rst
odoo/addons/sale_commission_salesman/readme/CONTRIBUTORS.rst
odoo/addons/sale_commission_salesman/readme/CREDITS.rst
odoo/addons/sale_commission_salesman/readme/DESCRIPTION.rst
odoo/addons/sale_commission_salesman/readme/USAGE.rst
odoo/addons/sale_commission_salesman/static/description/icon.png
odoo/addons/sale_commission_salesman/static/description/icon.svg
odoo/addons/sale_commission_salesman/static/description/index.html
odoo/addons/sale_commission_salesman/tests/__init__.py
odoo/addons/sale_commission_salesman/tests/test_sale_commission_salesman.py
odoo/addons/sale_commission_salesman/views/res_partner_views.xml
odoo12_addon_sale_commission_salesman-12.0.1.0.0.99.dev8.dist-info/METADATA
odoo12_addon_sale_commission_salesman-12.0.1.0.0.99.dev8.dist-info/WHEEL
odoo12_addon_sale_commission_salesman-12.0.1.0.0.99.dev8.dist-info/top_level.txt
odoo12_addon_sale_commission_salesman-12.0.1.0.0.99.dev8.dist-info/RECORD
